eonapi/__init__.py
eonapi/api.py
eonapi/cli.py
eonapi/database.py
eonapi/server.py
eonapi-0.5.0.dist-info/METADATA
eonapi-0.5.0.dist-info/WHEEL
eonapi-0.5.0.dist-info/entry_points.txt
eonapi-0.5.0.dist-info/licenses/LICENSE
eonapi-0.5.0.dist-info/RECORD
