Metadata-Version: 2.4
Name: eonapi
Version: 0.5.0
Summary: CLI tool for retrieving and analyzing electricity/gas consumption data from Eon Next API
Project-URL: Homepage, https://github.com/tomdyson/eonapi
Project-URL: Repository, https://github.com/tomdyson/eonapi
Project-URL: Issues, https://github.com/tomdyson/eonapi/issues
Project-URL: Documentation, https://github.com/tomdyson/eonapi#readme
Author-email: Tom <tom@naive.co.uk>
License: MIT
License-File: LICENSE
Keywords: api,cli,consumption,electricity,energy,eon,eon-next,gas,smart-meter
Classifier: Development Status :: 4 - Beta
Classifier: Environment :: Console
Classifier: Intended Audience :: Developers
Classifier: Intended Audience :: End Users/Desktop
Classifier: License :: OSI Approved :: MIT License
Classifier: Operating System :: OS Independent
Classifier: Programming Language :: Python :: 3
Classifier: Programming Language :: Python :: 3.9
Classifier: Programming Language :: Python :: 3.10
Classifier: Programming Language :: Python :: 3.11
Classifier: Programming Language :: Python :: 3.12
Classifier: Programming Language :: Python :: 3.13
Classifier: Topic :: Home Automation
Classifier: Topic :: Utilities
Classifier: Typing :: Typed
Requires-Python: >=3.9
Requires-Dist: click>=8.0.0
Requires-Dist: httpx>=0.23.0
Requires-Dist: python-dateutil>=2.8.0
Provides-Extra: ui
Requires-Dist: fastapi>=0.104.0; extra == 'ui'
Requires-Dist: uvicorn[standard]>=0.24.0; extra == 'ui'
